earthkit_plots_default_styles/__init__.py
earthkit_plots_default_styles/_version.py
earthkit_plots_default_styles/schema.yml
earthkit_plots_default_styles/identities/mean-sea-level-pressure.yml
earthkit_plots_default_styles/identities/near-surface-air-temperature.yml
earthkit_plots_default_styles/identities/river-discharge.yml
earthkit_plots_default_styles/identities/sea-surface-temperature.yml
earthkit_plots_default_styles/identities/snow-water-equivalent.yml
earthkit_plots_default_styles/identities/soil-wetness-index.yml
earthkit_plots_default_styles/identities/temperature-at-850hPa.yml
earthkit_plots_default_styles/identities/total-precipitation.yml
earthkit_plots_default_styles/identities/total-runoff-water-equivalent.yml
earthkit_plots_default_styles/identities/wind-gust-at-10m-in-last-6-hours.yml
earthkit_plots_default_styles/styles/mean-sea-level-pressure.yml
earthkit_plots_default_styles/styles/near-surface-air-temperature.yml
earthkit_plots_default_styles/styles/river-discharge.yml
earthkit_plots_default_styles/styles/sea-surface-temperature.yml
earthkit_plots_default_styles/styles/snow-water-equivalent.yml
earthkit_plots_default_styles/styles/soil-wetness-index.yml
earthkit_plots_default_styles/styles/temperature-at-850hPa.yml
earthkit_plots_default_styles/styles/total-precipitation.yml
earthkit_plots_default_styles/styles/total-runoff-water-equivalent.yml
earthkit_plots_default_styles/styles/wind-gust-at-10m-in-last-6-hours.yml
earthkit_plots_default_styles/styles/wind-speed-at-10m.yml
earthkit_plots_default_styles-0.1.2.dist-info/licenses/LICENSE
earthkit_plots_default_styles-0.1.2.dist-info/METADATA
earthkit_plots_default_styles-0.1.2.dist-info/WHEEL
earthkit_plots_default_styles-0.1.2.dist-info/entry_points.txt
earthkit_plots_default_styles-0.1.2.dist-info/top_level.txt
earthkit_plots_default_styles-0.1.2.dist-info/RECORD
